{
    "Gamma Case": 18.51,
    "Falchion Case": 6.4,
    "Huntsman Weapon Case": 38.0,
    "Chroma Case": 22.56,
    "Glove Case": 58.92,
    "Revolver Case": 14.58,
    "Fracture Case": 2.78,
    "Recoil Case": 1.81,
    "Revolution Case": 2.13,
    "Kilowatt Case": 1.91,
    "Gallery Case": 5.87,
    "Shadow Case": 7.29,
    "Spectrum Case": 18.28,
    "Winter Offensive Weapon Case": 31.9,
    "Operation Hydra Case": 131.3,
    "Operation Vanguard Weapon Case": 20.39,
    "CS:GO Weapon Case": 366.96,
    "Horizon Case": 7.63,
    "Clutch Case": 4.06,
    "Operation Bravo Case": 181.13,
    "Operation Riptide Case": 54.2,
    "Operation Breakout Weapon Case": 48.93,
    "Operation Phoenix Weapon Case": 19.58,
    "CS20 Case": 5.76,
    "Chroma 2 Case": 19.58,
    "Spectrum 2 Case": 16.69,
    "Prisma 2 Case": 6.87,
    "Prisma Case": 6.87,
    "Snakebite Case": 2.89,
    "CS:GO Weapon Case 3": 39.0,
    "Operation Broken Fang Case": 38.72,
    "CS:GO Weapon Case 2": 52.52,
    "Dreams & Nightmares Case": 8.69,
    "Shattered Web Case": 25.89,
    "Chroma 3 Case": 18.69,
    "Danger Zone Case": 6.86,
    "Operation Wildfire Case": 16.22
}